{
  "generated_at": "2026-03-21T04:52:16.512080+00:00",
  "status": "Elevated Pressure",
  "composite_score": 54,
  "scores": {
    "housing": 53,
    "cost_of_living": 59,
    "employment": 56,
    "morale": 42,
    "benefits": 57,
    "media": 56
  },
  "summary": [
    "System under elevated pressure",
    "Affordability pressure elevated",
    "Housing strain elevated",
    "Employment strain elevated"
  ],
  "narrative": [
    "Composite score: 54.",
    "Highest pressure domain: cost of living (59).",
    "Second highest pressure domain: benefits (57).",
    "Most stable domain: morale (42).",
    "Sources analyzed successfully: 13 of 20.",
    "FRED unemployment reference: 4.4%."
  ],
  "display_trends": {
    "composite": {
      "current": 54,
      "delta_7": -2,
      "delta_30": -2,
      "direction": "down",
      "arrow": "\u25bc",
      "color": "red",
      "sparkline": [
        56,
        54,
        54,
        54
      ]
    },
    "housing": {
      "current": 53,
      "delta_7": 1,
      "delta_30": 1,
      "direction": "flat",
      "arrow": "\u2192",
      "color": "yellow",
      "sparkline": [
        52,
        53,
        53,
        53
      ]
    },
    "cost_of_living": {
      "current": 59,
      "delta_7": -6,
      "delta_30": -6,
      "direction": "down",
      "arrow": "\u25bc",
      "color": "red",
      "sparkline": [
        65,
        58,
        58,
        59
      ]
    },
    "employment": {
      "current": 56,
      "delta_7": 2,
      "delta_30": 2,
      "direction": "up",
      "arrow": "\u25b2",
      "color": "green",
      "sparkline": [
        54,
        56,
        56,
        56
      ]
    },
    "morale": {
      "current": 42,
      "delta_7": -18,
      "delta_30": -18,
      "direction": "down",
      "arrow": "\u25bc",
      "color": "red",
      "sparkline": [
        60,
        41,
        41,
        42
      ]
    },
    "benefits": {
      "current": 57,
      "delta_7": 4,
      "delta_30": 4,
      "direction": "up",
      "arrow": "\u25b2",
      "color": "green",
      "sparkline": [
        53,
        57,
        57,
        57
      ]
    },
    "media": {
      "current": 56,
      "delta_7": 2,
      "delta_30": 2,
      "direction": "up",
      "arrow": "\u25b2",
      "color": "green",
      "sparkline": [
        54,
        57,
        57,
        56
      ]
    }
  },
  "meta": {
    "source_count": 20,
    "successful_sources": 13,
    "failed_sources": 7,
    "fred_api_key_present": true,
    "news_api_key_present": false,
    "tier_counts": {
      "tier_1": 10,
      "tier_2": 10,
      "tier_3": 0
    },
    "type_counts": {
      "policy": 4,
      "operational": 10,
      "media": 6,
      "sentiment": 0,
      "unknown": 0
    },
    "history_points": 4,
    "source_signal_map_loaded": true
  },
  "fred": {
    "cpi": 327.46,
    "unemployment": 4.4,
    "consumer_sentiment_proxy": 56.4
  },
  "fred_domain_adjustments": {
    "housing": 2,
    "cost_of_living": 0,
    "employment": 0,
    "morale": -10,
    "benefits": 0,
    "media": 0
  },
  "newsapi": {
    "enabled": false,
    "queries_run": 0,
    "articles_used": 0,
    "errors": [
      "missing_api_key"
    ]
  },
  "sources": [
    {
      "key": "va_news",
      "url": "https://news.va.gov",
      "tier": "tier_1",
      "type": "operational",
      "mapped_domain": "benefits",
      "ok": true,
      "status_code": 200,
      "freshness": 50,
      "source_kind": "source_plan"
    },
    {
      "key": "va_press",
      "url": "https://www.va.gov/opa/pressrel",
      "tier": "tier_1",
      "type": "operational",
      "mapped_domain": "benefits",
      "ok": true,
      "status_code": 200,
      "freshness": 50,
      "source_kind": "source_plan"
    },
    {
      "key": "defense_news",
      "url": "https://www.defense.gov/News",
      "tier": "tier_1",
      "type": "operational",
      "mapped_domain": "employment",
      "ok": false,
      "status_code": 403,
      "freshness": 50,
      "source_kind": "source_plan"
    },
    {
      "key": "federal_register",
      "url": "https://www.federalregister.gov",
      "tier": "tier_1",
      "type": "policy",
      "mapped_domain": "policy",
      "ok": true,
      "status_code": 200,
      "freshness": 50,
      "source_kind": "source_plan"
    },
    {
      "key": "congress",
      "url": "https://www.congress.gov",
      "tier": "tier_1",
      "type": "policy",
      "mapped_domain": "policy",
      "ok": false,
      "status_code": 403,
      "freshness": 50,
      "source_kind": "source_plan"
    },
    {
      "key": "senate_va",
      "url": "https://www.veterans.senate.gov",
      "tier": "tier_1",
      "type": "policy",
      "mapped_domain": "benefits",
      "ok": true,
      "status_code": 200,
      "freshness": 50,
      "source_kind": "source_plan"
    },
    {
      "key": "house_va",
      "url": "https://veterans.house.gov",
      "tier": "tier_1",
      "type": "policy",
      "mapped_domain": "benefits",
      "ok": true,
      "status_code": 200,
      "freshness": 95,
      "source_kind": "source_plan"
    },
    {
      "key": "stripes",
      "url": "https://www.stripes.com",
      "tier": "tier_1",
      "type": "media",
      "mapped_domain": "general",
      "ok": true,
      "status_code": 200,
      "freshness": 95,
      "source_kind": "source_plan"
    },
    {
      "key": "military_com",
      "url": "https://www.military.com",
      "tier": "tier_1",
      "type": "media",
      "mapped_domain": "general",
      "ok": true,
      "status_code": 200,
      "freshness": 95,
      "source_kind": "source_plan"
    },
    {
      "key": "military_times",
      "url": "https://www.militarytimes.com",
      "tier": "tier_1",
      "type": "media",
      "mapped_domain": "general",
      "ok": true,
      "status_code": 200,
      "freshness": 95,
      "source_kind": "source_plan"
    },
    {
      "key": "task_purpose",
      "url": "https://taskandpurpose.com",
      "tier": "tier_2",
      "type": "media",
      "mapped_domain": "general",
      "ok": true,
      "status_code": 200,
      "freshness": 50,
      "source_kind": "source_plan"
    },
    {
      "key": "defense_news_media",
      "url": "https://www.defensenews.com",
      "tier": "tier_2",
      "type": "media",
      "mapped_domain": "general",
      "ok": true,
      "status_code": 200,
      "freshness": 95,
      "source_kind": "source_plan"
    },
    {
      "key": "defense_one",
      "url": "https://www.defenseone.com",
      "tier": "tier_2",
      "type": "media",
      "mapped_domain": "policy",
      "ok": true,
      "status_code": 200,
      "freshness": 95,
      "source_kind": "source_plan"
    },
    {
      "key": "army_news",
      "url": "https://www.army.mil/news",
      "tier": "tier_2",
      "type": "operational",
      "mapped_domain": "employment",
      "ok": true,
      "status_code": 200,
      "freshness": 50,
      "source_kind": "source_plan"
    },
    {
      "key": "navy_news",
      "url": "https://www.navy.mil/Press-Office/News-Stories",
      "tier": "tier_2",
      "type": "operational",
      "mapped_domain": "employment",
      "ok": false,
      "status_code": 403,
      "freshness": 50,
      "source_kind": "source_plan"
    },
    {
      "key": "airforce_news",
      "url": "https://www.af.mil/News",
      "tier": "tier_2",
      "type": "operational",
      "mapped_domain": "employment",
      "ok": false,
      "status_code": 403,
      "freshness": 50,
      "source_kind": "source_plan"
    },
    {
      "key": "marines_news",
      "url": "https://www.marines.mil/News",
      "tier": "tier_2",
      "type": "operational",
      "mapped_domain": "employment",
      "ok": false,
      "status_code": 403,
      "freshness": 50,
      "source_kind": "source_plan"
    },
    {
      "key": "spaceforce_news",
      "url": "https://www.spaceforce.mil/News",
      "tier": "tier_2",
      "type": "operational",
      "mapped_domain": "employment",
      "ok": false,
      "status_code": 403,
      "freshness": 50,
      "source_kind": "source_plan"
    },
    {
      "key": "nrd",
      "url": "https://www.nrd.gov",
      "tier": "tier_2",
      "type": "operational",
      "mapped_domain": "support",
      "ok": true,
      "status_code": 200,
      "freshness": 64,
      "source_kind": "source_plan"
    },
    {
      "key": "military_one_source",
      "url": "https://www.militaryonesource.mil",
      "tier": "tier_2",
      "type": "operational",
      "mapped_domain": "support",
      "ok": false,
      "status_code": 403,
      "freshness": 50,
      "source_kind": "source_plan"
    }
  ],
  "newsapi_sources": []
}